Inukshuk-0.1.2.dist-info/DESCRIPTION.rst
Inukshuk-0.1.2.dist-info/METADATA
Inukshuk-0.1.2.dist-info/RECORD
Inukshuk-0.1.2.dist-info/WHEEL
Inukshuk-0.1.2.dist-info/metadata.json
Inukshuk-0.1.2.dist-info/top_level.txt
inukshuk/__init__.py
inukshuk/compiler.py
inukshuk/engine.py
inukshuk/lexer.py
inukshuk/loader.py
inukshuk/optimizer.py
inukshuk/parser.py
inukshuk/rendering.py
inukshuk/template.py
inukshuk/util.py
inukshuk/version.py
inukshuk/ext/__init__.py
inukshuk/ext/core.py
inukshuk/nodes/__init__.py
inukshuk/nodes/base.py
inukshuk/nodes/const.py
inukshuk/nodes/expression.py
inukshuk/nodes/filters.py
inukshuk/nodes/funcbase.py
inukshuk/nodes/operators.py
inukshuk/nodes/tests.py
inukshuk/nodes/text.py
inukshuk/nodes/wrapper.py
tests/__init__.py
tests/conftest.py
tests/test_basic.py
tests/test_core.py
tests/test_filter.py
tests/test_funccalls.py
tests/test_whitespace.py
tests/lexer/test_lexer.yaml
tests/lexer/test_numbers.yaml
tests/lexer/test_whitespace.yaml
tests/parser/test_filter.yaml
tests/parser/test_operators.yaml
tests/parser/test_parser.yaml
tests/parser/test_statements.yaml
tests/parser/test_tests.yaml
tests/parser/test_whitespace.yaml
tests/template/test_autoescape.yaml
tests/template/test_comments.yaml
tests/template/test_expressions.yaml
tests/template/test_extends.yaml
tests/template/test_filter.yaml
tests/template/test_for.yaml
tests/template/test_if.yaml
tests/template/test_import.yaml
tests/template/test_include.yaml
tests/template/test_macros.yaml
tests/template/test_operators.yaml
tests/template/test_raw.yaml
tests/template/test_set.yaml
tests/template/test_simple.yaml
tests/template/test_tests.yaml
