Metadata-Version: 2.0
Name: Inukshuk
Version: 0.1.2
Summary: A template engine.
Home-page: https://bolt80.com/inukshuk
Author: Ludovic Chabant
Author-email: ludovic@chabant.com
License: Apache License 2.0
Keywords: template engine
Platform: UNKNOWN
Requires-Dist: MarkupSafe (>=1.0)
Requires-Dist: strict-rfc3339 (>=0.7)
